setup.py
PyExpressions.egg-info/PKG-INFO
PyExpressions.egg-info/SOURCES.txt
PyExpressions.egg-info/dependency_links.txt
PyExpressions.egg-info/top_level.txt
pyexpressions/__init__.py
pyexpressions/lagrangeinterpolation.py
pyexpressions/util.py