Metadata-Version: 1.1
Name: PyExpressions
Version: 0.0.0.1.dev0
Summary: Mathematical expressions library
Home-page: http://github.com/alvinwan/PyExpressions
Author: Alvin Wan, Nathan Pucheril
Author-email: UNKNOWN
License: Apache
Download-URL: https://github.com/alvinwan/PyExpressions/archive/v0.0.0.1dev.zip
Platform: UNKNOWN
Classifier: Topic :: Utilities
